Metadata-Version: 1.0
Name: bunch
Version: 1.0.0
Summary: A dot-accessible dictionary (a la JavaScript objects)
Home-page: http://tire.less.ly/hacking/bunch
Author: David Schoonover
Author-email: dsc@less.ly
License: MIT
Download-URL: http://pypi.python.org/packages/source/b/bunch/bunch-1.0.0.tar.gz
Keywords: bunch,dict,mapping,container,collection
Platform: UNKNOWN
Classifier: Programming Language :: Python
Classifier: Development Status :: 5 - Production/Stable
Classifier: License :: OSI Approved :: MIT License
Classifier: Operating System :: OS Independent
Classifier: Intended Audience :: Developers
Classifier: Topic :: Software Development
Classifier: Topic :: Software Development :: Libraries
Classifier: Topic :: Utilities
